tcmarkers/__init__.py
tcmarkers/markers.py
tcmarkers-0.0.3.dist-info/LICENSE
tcmarkers-0.0.3.dist-info/METADATA
tcmarkers-0.0.3.dist-info/WHEEL
tcmarkers-0.0.3.dist-info/top_level.txt
tcmarkers-0.0.3.dist-info/zip-safe
tcmarkers-0.0.3.dist-info/RECORD
