Metadata-Version: 2.1
Name: tcmarkers
Version: 0.0.3
Summary: Tropical Storm and Hurricane Markers for Matplotlib
Home-page: https://github.com/abrammer/tc_markers
License: BSD 3-Clause License
Platform: UNKNOWN
Classifier: Programming Language :: Python :: 3
License-File: LICENSE
Requires-Dist: matplotlib
Requires-Dist: numpy
